{
  "pensamentos": [
    {
      "id": "1",
      "conteudo": "Que bom que vc veio",
      "autoria": "Nay",
      "modelo": "modelo1"
    },
    {
      "id": "2",
      "conteudo": "Estudando Angular",
      "autoria": "Dev Alura",
      "modelo": "modelo2"
    },
    {
      "id": "3",
      "conteudo": "Angular é o melhor'",
      "autoria": "Dev Alura",
      "modelo": "modelo3"
    },
    {
      "id": "f559",
      "conteudo": "Pensamento de teste",
      "autoria": "Dev Angular",
      "modelo": "modelo3"
    },
    {
      "id": "ca7b",
      "conteudo": "pensamento teste 2",
      "autoria": "dev teste",
      "modelo": "modelo2"
    }
  ]
}